striplog/__init__.py
striplog/_version.py
striplog/canstrat.py
striplog/canstrat_codes.py
striplog/component.py
striplog/defaults.py
striplog/description.py
striplog/hatches.py
striplog/interval.py
striplog/legend.py
striplog/lexicon.py
striplog/logo.py
striplog/markov.py
striplog/position.py
striplog/rock.py
striplog/striplog.py
striplog/templates.py
striplog/utils.py
striplog-0.9.2.dist-info/AUTHORS.md
striplog-0.9.2.dist-info/LICENSE
striplog-0.9.2.dist-info/METADATA
striplog-0.9.2.dist-info/WHEEL
striplog-0.9.2.dist-info/top_level.txt
striplog-0.9.2.dist-info/RECORD
