Metadata-Version: 2.1
Name: striplog
Version: 0.9.2
Summary: Lithology and stratigraphic logs for wells and outcrop.
Home-page: https://github.com/agile-geoscience/striplog
Author: The Striplog Authors
Author-email: hello@agilescientific.com
License: UNKNOWN
Platform: UNKNOWN
Classifier: Intended Audience :: Science/Research
Classifier: Development Status :: 4 - Beta
Classifier: Natural Language :: English
Classifier: Programming Language :: Python :: 3.6
Classifier: Programming Language :: Python :: 3.7
Classifier: Programming Language :: Python :: 3.8
Classifier: Programming Language :: Python :: 3.9
Classifier: Programming Language :: Python :: 3.10
Classifier: License :: OSI Approved :: Apache Software License
Classifier: Operating System :: OS Independent
Requires-Python: >=3.6
Provides-Extra: test
Provides-Extra: docs
Provides-Extra: dev
License-File: LICENSE
License-File: AUTHORS.md
